focont/__init__.py
focont/accessories.py
focont/foc.py
focont/system.py
focont-1.0.1.dist-info/METADATA
focont-1.0.1.dist-info/WHEEL
focont-1.0.1.dist-info/licenses/LICENSE.md
focont-1.0.1.dist-info/RECORD
