Metadata-Version: 2.3
Name: focont
Version: 1.0.1
Summary: Fixed order controller design tool
Project-URL: Homepage, https://github.com/dmrokan/focont
Project-URL: Documentation, https://github.com/dmrokan/focont/blob/main/doc/focont.md
Project-URL: Repository, https://github.com/dmrokan/focont
Project-URL: Bug Tracker, https://github.com/dmrokan/focont/issues
Project-URL: Changelog, https://github.com/dmrokan/focont/blob/main/CHANGELOG.md
Author-email: Okan Demir <okndemir@gmail.com>
Maintainer-email: Okan Demir <okndemir@gmail.com>
License: Copyright (c) 2024 Okan Demir
License-File: LICENSE.md
Keywords: conroller-design,control,optimal-control,static-output-feedback,systems
Classifier: License :: OSI Approved :: MIT License
Classifier: Operating System :: OS Independent
Classifier: Programming Language :: Python :: 3
Requires-Python: >=3.8
Requires-Dist: numpy
Requires-Dist: scipy
Provides-Extra: dev
Requires-Dist: black; extra == 'dev'
Requires-Dist: mypy; extra == 'dev'
Requires-Dist: pytest; extra == 'dev'
Requires-Dist: pytest-randomly; extra == 'dev'
Provides-Extra: test
Requires-Dist: pytest; extra == 'test'
Requires-Dist: pytest-randomly; extra == 'test'
